PyPowerDNS/__init__.py
PyPowerDNS/api.py
PyPowerDNS/exceptions.py
PyPowerDNS/objects.py
PyPowerDNS-2022.4.1.dist-info/LICENSE
PyPowerDNS-2022.4.1.dist-info/METADATA
PyPowerDNS-2022.4.1.dist-info/WHEEL
PyPowerDNS-2022.4.1.dist-info/top_level.txt
PyPowerDNS-2022.4.1.dist-info/RECORD
