Metadata-Version: 2.1
Name: PyPowerDNS
Version: 2022.4.1
Summary: Python 3 module to talk to authoritative PowerDNS API.
Home-page: https://github.com/TheDJVG/PyPowerDNS
Author: D. van Gorkum
Author-email: djvg@djvg.net
License: UNKNOWN
Platform: UNKNOWN
Classifier: Programming Language :: Python :: 3
Classifier: License :: OSI Approved :: MIT License
Requires-Python: >=3.6
License-File: LICENSE
Requires-Dist: requests
